{
  "type": "Feature",
  "stac_version": "1.0.0",
  "id": "20230103_203256_1p0a_LNO_1_DF_134_00533_83",
  "properties": {
    "ssys:targets": [
      "Mars"
    ],
    "processing:level": "footprint",
    "proj:wkt2": "GEOGCRS[\"Mars (2015) - Sphere / Ocentric\",\n                    DATUM[\"Mars (2015) - Sphere\",\n                        ELLIPSOID[\"Mars (2015) - Sphere\", 3396190, 0,\n                    LENGTHUNIT[\"metre\", 1, ID[\"EPSG\", 9001]]],\n                    ANCHOR[\"Viking 1 lander : 47.95137 W\"]],\n                    PRIMEM[\"Reference Meridian\", 0,\n                    ANGLEUNIT[\"degree\", 0.0174532925199433, ID[\"EPSG\", 9122]]],\n            CS[ellipsoidal, 2],\n                AXIS[\"geodetic latitude (Lat)\", north,\n    ORDER[1],\n                    ANGLEUNIT[\"degree\", 0.0174532925199433]],\n                AXIS[\"geodetic longitude (Lon)\", east,\n    ORDER[2],\n                    ANGLEUNIT[\"degree\", 0.0174532925199433]],\n            ID[\"IAU\", 49900, 2015],\n            REMARK[\"Use semi-major radius as sphere radius for interoperability. Source of IAU Coordinate systems:\n    doi://10.1007/s10569-017-9805-5\"]]",
    "datetime": "2023-01-03T20:43:09.930159Z"
  },
  "geometry": {
    "type": "Polygon",
    "coordinates": [
      [
        [
          129.2412582744023,
          1.915879909395776
        ],
        [
          128.9707507403709,
          1.9790631323651118
        ],
        [
          128.96899561117675,
          1.9715522648326869
        ],
        [
          128.9428554405273,
          1.818002434891408
        ],
        [
          129.21359544661408,
          1.7558927723551025
        ],
        [
          129.21531988287015,
          1.7634090061388568
        ],
        [
          129.2412582744023,
          1.915879909395776
        ]
      ]
    ]
  },
  "links": [
    {
      "rel": "root",
      "href": "/Users/fandrieu/Documents/Nomad_STAC/output/catalog.json",
      "type": "application/json",
      "title": "ExoMars NOMAD/LNO footprints"
    },
    {
      "rel": "collection",
      "href": "/Users/fandrieu/Documents/Nomad_STAC/output/5 days lno - collection/collection.json",
      "type": "application/json",
      "title": "5 days lno - PySTAC prototype"
    },
    {
      "rel": "parent",
      "href": "/Users/fandrieu/Documents/Nomad_STAC/output/5 days lno - collection/collection.json",
      "type": "application/json",
      "title": "5 days lno - PySTAC prototype"
    }
  ],
  "assets": {},
  "bbox": [
    108.84133849035024,
    -58.97816863313544,
    169.40510219635513,
    70.92870215060987
  ],
  "stac_extensions": [
    "https://raw.githubusercontent.com/thareUSGS/ssys/main/json-schema/schema.json",
    "https://stac-extensions.github.io/file/v2.1.0/schema.json",
    "https://stac-extensions.github.io/projection/v1.1.0/schema.json"
  ],
  "collection": "5 days lno - collection"
}